{
  "date": "2026-03-08",
  "has_sessions": false,
  "session_count": 0,
  "test_report": {
    "date": "2026-03-08",
    "status": "PASS",
    "duration_frames": null,
    "source": "static_analysis",
    "errors": [],
    "state_transitions": [
      "tutorial_mode_select",
      "difficulty_select",
      "endless_difficulty_select",
      "tutorial_intro",
      "play",
      "tutorial_dash",
      "menu"
    ],
    "logs_captured": 78,
    "events": {
      "state_transitions": 7,
      "game_events": 67,
      "gameover_events": 3
    },
    "exit_state": "analysis_complete",
    "metadata": {
      "title": "Cave Escape",
      "description": "Navigate a dangerous cave while avoiding enemies in adventure mode or survive infinite waves in endless mode. Progress through five escalating levels in adventure mode, or face endless waves of enemies with difficulty scaling (easy/normal/hard). Use arrow keys to move and the dash mechanic (X button) to dodge. Master the dash mechanic - Level 4 teaches tight corridor navigation while Level 5 presents expert rapid-dash challenges. In endless mode, survive waves, rack up score multipliers, and beat your best score.",
      "genres": [
        "adventure",
        "action"
      ],
      "difficulty": 3,
      "completion_status": "polished"
    }
  },
  "metrics": {}
}